{
  "0": {
    "start": 12.259,
    "end": 12.819,
    "transcript": "do you have"
  },
  "1": {
    "start": 13.23,
    "end": 15.65859,
    "transcript": "a pile of rocks"
  },
  "2": {
    "start": 18.31,
    "end": 19.539,
    "transcript": "near the sea"
  },
  "3": {
    "start": 20.98873,
    "end": 21.399,
    "transcript": "oh"
  },
  "4": {
    "start": 21.99246,
    "end": 23.25069,
    "transcript": "do you have the sign"
  },
  "5": {
    "start": 23.59,
    "end": 24.44449,
    "transcript": "sign"
  },
  "6": {
    "start": 26.35,
    "end": 29.719,
    "transcript": "to the beach says to the beach"
  },
  "7": {
    "start": 31.0,
    "end": 32.319,
    "transcript": "no to the beach"
  },
  "8": {
    "start": 33.79,
    "end": 35.399,
    "transcript": "press it pressed it"
  },
  "9": {
    "start": 35.59,
    "end": 36.19,
    "transcript": "yes"
  },
  "10": {
    "start": 36.94,
    "end": 38.869,
    "transcript": "do you have a car"
  },
  "11": {
    "start": 40.05,
    "end": 44.78,
    "transcript": "the red car red car oh do you have a taxi"
  },
  "12": {
    "start": 44.999,
    "end": 46.14,
    "transcript": "you have a taxi"
  },
  "13": {
    "start": 47.29,
    "end": 49.219,
    "transcript": "do you have uhm is"
  },
  "14": {
    "start": 49.81,
    "end": 56.649,
    "transcript": "you know the uh do you have a smoothie truck smoothie thing"
  },
  "15": {
    "start": 58.95,
    "end": 61.65785,
    "transcript": "no mine says smoothies"
  },
  "16": {
    "start": 62.06,
    "end": 63.8,
    "transcript": "peach yeah"
  },
  "17": {
    "start": 64.09991,
    "end": 66.709,
    "transcript": "and it says plumbs and plumbs underneath"
  },
  "18": {
    "start": 68.77,
    "end": 69.64045,
    "transcript": "yes"
  },
  "19": {
    "start": 74.68,
    "end": 75.8,
    "transcript": "yes"
  },
  "20": {
    "start": 81.81,
    "end": 83.219,
    "transcript": "yes yes"
  },
  "21": {
    "start": 86.15,
    "end": 87.37113,
    "transcript": "green"
  },
  "22": {
    "start": 88.86,
    "end": 89.569,
    "transcript": "yes"
  },
  "23": {
    "start": 96.0,
    "end": 97.05,
    "transcript": "yes"
  },
  "24": {
    "start": 98.19,
    "end": 100.61823,
    "transcript": "he says one two three push"
  },
  "25": {
    "start": 104.62,
    "end": 105.319,
    "transcript": "pressed it"
  },
  "26": {
    "start": 110.12,
    "end": 112.37506,
    "transcript": "no which guy"
  },
  "27": {
    "start": 114.43,
    "end": 117.689,
    "transcript": "oh yeah okay i pressed it pressed it"
  },
  "28": {
    "start": 120.54,
    "end": 122.669,
    "transcript": "garbage bin where is the garbage bin"
  },
  "29": {
    "start": 123.12,
    "end": 123.549,
    "transcript": "oh yeah"
  },
  "30": {
    "start": 123.8,
    "end": 125.149,
    "transcript": "yeah blue i have it"
  },
  "31": {
    "start": 131.72,
    "end": 133.55458,
    "transcript": "and tennis balls"
  },
  "32": {
    "start": 135.1,
    "end": 135.939,
    "transcript": "yes she does"
  },
  "33": {
    "start": 137.39,
    "end": 138.179,
    "transcript": "she does"
  },
  "34": {
    "start": 141.67,
    "end": 143.3334,
    "transcript": "tennis ball i pressed it"
  },
  "35": {
    "start": 146.43,
    "end": 147.079,
    "transcript": "yes"
  },
  "36": {
    "start": 148.92,
    "end": 150.59837,
    "transcript": "yes"
  },
  "37": {
    "start": 153.05091,
    "end": 155.20839,
    "transcript": "uh where no"
  },
  "38": {
    "start": 161.25107,
    "end": 162.60599,
    "transcript": "sandcastle"
  },
  "39": {
    "start": 163.07946,
    "end": 164.55746,
    "transcript": "uh yeah"
  },
  "40": {
    "start": 166.31,
    "end": 167.64358,
    "transcript": "yes"
  },
  "41": {
    "start": 169.29,
    "end": 175.26381,
    "transcript": "yes you have a a sign that says love shack live tonight"
  },
  "42": {
    "start": 178.5,
    "end": 182.63392,
    "transcript": "it says love shack live tonight press it"
  },
  "43": {
    "start": 184.76,
    "end": 185.729,
    "transcript": "yes yes"
  },
  "44": {
    "start": 189.63068,
    "end": 190.729,
    "transcript": "uh no"
  },
  "45": {
    "start": 191.16615,
    "end": 192.499,
    "transcript": "oh yes yes i do"
  },
  "46": {
    "start": 194.25,
    "end": 195.38571,
    "transcript": "three"
  },
  "47": {
    "start": 201.969,
    "end": 202.9914,
    "transcript": "yes"
  },
  "48": {
    "start": 205.36,
    "end": 206.39048,
    "transcript": "no"
  },
  "49": {
    "start": 207.96,
    "end": 209.59472,
    "transcript": "okay pressed"
  },
  "50": {
    "start": 212.21,
    "end": 214.53125,
    "transcript": "where oh yeah yeah"
  },
  "51": {
    "start": 218.39,
    "end": 219.48476,
    "transcript": "yes"
  },
  "52": {
    "start": 221.85624,
    "end": 225.82664,
    "transcript": "uhm is there taxi white"
  },
  "53": {
    "start": 227.84,
    "end": 229.989,
    "transcript": "is that taxi is there a taxi"
  },
  "54": {
    "start": 232.92,
    "end": 235.0002,
    "transcript": "uh mostly white"
  },
  "55": {
    "start": 238.71741,
    "end": 241.08883,
    "transcript": "yeah"
  },
  "56": {
    "start": 243.06431,
    "end": 244.68454,
    "transcript": "yes"
  },
  "57": {
    "start": 248.65693,
    "end": 250.49039,
    "transcript": "uh yes"
  },
  "58": {
    "start": 252.71,
    "end": 253.96866,
    "transcript": "yes"
  },
  "59": {
    "start": 259.77,
    "end": 260.269,
    "transcript": "yes"
  },
  "60": {
    "start": 262.6655,
    "end": 264.0266,
    "transcript": "blue"
  },
  "61": {
    "start": 267.64,
    "end": 271.529,
    "transcript": "yes oh no there's no which man"
  },
  "62": {
    "start": 274.93,
    "end": 276.019,
    "transcript": "yeah yeah"
  },
  "63": {
    "start": 279.06,
    "end": 279.709,
    "transcript": "yes"
  },
  "64": {
    "start": 281.54,
    "end": 282.249,
    "transcript": "yes"
  },
  "65": {
    "start": 284.84,
    "end": 289.65696,
    "transcript": "yes"
  },
  "66": {
    "start": 291.31,
    "end": 292.45506,
    "transcript": "yes"
  },
  "67": {
    "start": 295.19,
    "end": 299.479,
    "transcript": "do you mean a blender measuring thing i don't know is it"
  },
  "68": {
    "start": 299.69,
    "end": 302.61701,
    "transcript": "measuring it might be a blender"
  },
  "69": {
    "start": 303.13,
    "end": 303.399,
    "transcript": "is"
  },
  "70": {
    "start": 310.58,
    "end": 315.70864,
    "transcript": "is it white at the top but and gray at the bottom oh i have that i have that"
  },
  "71": {
    "start": 322.57823,
    "end": 323.289,
    "transcript": "it's"
  },
  "72": {
    "start": 323.61,
    "end": 327.36655,
    "transcript": "it's green red grey and"
  },
  "73": {
    "start": 328.86,
    "end": 330.749,
    "transcript": "yeah and peach yeah yeah"
  },
  "74": {
    "start": 334.17,
    "end": 335.999,
    "transcript": "yes yeah there"
  },
  "75": {
    "start": 341.27,
    "end": 343.48283,
    "transcript": "what yes she does"
  },
  "76": {
    "start": 346.61429,
    "end": 350.44887,
    "transcript": "uhm light blue light light blue"
  },
  "77": {
    "start": 353.21,
    "end": 353.569,
    "transcript": "yeah"
  },
  "78": {
    "start": 355.26,
    "end": 358.589,
    "transcript": "yes yeah and a blue thing a blue"
  },
  "79": {
    "start": 359.65,
    "end": 368.81088,
    "transcript": "bottoms yeah uhm"
  },
  "80": {
    "start": 374.12,
    "end": 376.96592,
    "transcript": "where do i press i don't know"
  },
  "81": {
    "start": 379.91,
    "end": 381.44,
    "transcript": "uhm do you mean"
  },
  "82": {
    "start": 381.68,
    "end": 384.12,
    "transcript": "in the big pile of rocks in like one"
  },
  "83": {
    "start": 385.45,
    "end": 388.229,
    "transcript": "yeah i have that no yeah"
  },
  "84": {
    "start": 396.64,
    "end": 397.24966,
    "transcript": "yeah"
  },
  "85": {
    "start": 399.02,
    "end": 401.409,
    "transcript": "yes it's blonde hair actually"
  },
  "86": {
    "start": 409.52,
    "end": 412.43902,
    "transcript": "yes yes"
  },
  "87": {
    "start": 414.37272,
    "end": 422.579,
    "transcript": "uh no i maybe uh i'll think uh is the bucket red the bucket red"
  },
  "88": {
    "start": 423.72,
    "end": 425.249,
    "transcript": "is the shovel yellow"
  },
  "89": {
    "start": 427.25,
    "end": 430.279,
    "transcript": "no it's yellow no oh orange orange yellow"
  },
  "90": {
    "start": 433.95,
    "end": 436.269,
    "transcript": "yeah the sand what about the sand"
  },
  "91": {
    "start": 437.43,
    "end": 443.59771,
    "transcript": "yes all sand is yellow"
  },
  "92": {
    "start": 446.3,
    "end": 448.34934,
    "transcript": "i know that c'mon uh"
  },
  "93": {
    "start": 454.98,
    "end": 455.999,
    "transcript": "yellow socks"
  },
  "94": {
    "start": 457.35,
    "end": 458.5846,
    "transcript": "yellow"
  },
  "95": {
    "start": 460.18,
    "end": 464.01999,
    "transcript": "press it"
  },
  "96": {
    "start": 466.44,
    "end": 466.899,
    "transcript": "yes"
  },
  "97": {
    "start": 469.38,
    "end": 470.119,
    "transcript": "yes"
  },
  "98": {
    "start": 474.06925,
    "end": 480.36344,
    "transcript": "uh yes yes"
  },
  "99": {
    "start": 482.60943,
    "end": 484.68723,
    "transcript": "uhm"
  },
  "100": {
    "start": 487.7,
    "end": 488.179,
    "transcript": "yes"
  },
  "101": {
    "start": 490.16,
    "end": 493.1393,
    "transcript": "yeah yeah"
  },
  "102": {
    "start": 495.24,
    "end": 495.929,
    "transcript": "yes"
  },
  "103": {
    "start": 497.66,
    "end": 499.26485,
    "transcript": "white yes yes"
  },
  "104": {
    "start": 502.53,
    "end": 505.04,
    "transcript": "yeah there is yeah"
  },
  "105": {
    "start": 509.70905,
    "end": 512.769,
    "transcript": "uhm in the middle of this both"
  },
  "106": {
    "start": 521.92,
    "end": 524.3,
    "transcript": "yes yes"
  },
  "107": {
    "start": 527.26,
    "end": 527.6393,
    "transcript": "yes"
  },
  "108": {
    "start": 528.47,
    "end": 529.61467,
    "transcript": "yes"
  },
  "109": {
    "start": 537.47,
    "end": 538.77,
    "transcript": "he's not saying hey"
  },
  "110": {
    "start": 539.69,
    "end": 540.639,
    "transcript": "hey paul"
  },
  "111": {
    "start": 542.08,
    "end": 543.75134,
    "transcript": "nothing"
  },
  "112": {
    "start": 547.88263,
    "end": 559.70152,
    "transcript": "uhm uh and uh think think c'mon"
  },
  "113": {
    "start": 560.98,
    "end": 564.40841,
    "transcript": "at least try and get one more let's try"
  },
  "114": {
    "start": 566.8614,
    "end": 569.95887,
    "transcript": "uh i don't see anything"
  },
  "115": {
    "start": 572.69,
    "end": 578.519,
    "transcript": "i don't see anything do you is the floaty pink"
  },
  "116": {
    "start": 579.9,
    "end": 585.55671,
    "transcript": "yup same uh what else is there"
  },
  "117": {
    "start": 586.83504,
    "end": 587.70162,
    "transcript": "what"
  },
  "118": {
    "start": 592.18,
    "end": 593.81222,
    "transcript": "i didn't do that"
  },
  "119": {
    "start": 595.41,
    "end": 603.129,
    "transcript": "maybe i did yeah i heard your blowing"
  },
  "120": {
    "start": 604.61,
    "end": 605.5,
    "transcript": "yeah"
  },
  "121": {
    "start": 608.08401,
    "end": 609.429,
    "transcript": "uhm"
  },
  "122": {
    "start": 611.15,
    "end": 618.19878,
    "transcript": "just press we to press finish don't we ended"
  }
}