{
  "0": {
    "start": 7.14,
    "end": 8.069,
    "transcript": "so"
  },
  "1": {
    "start": 8.67,
    "end": 12.359,
    "transcript": "so on like the top left corner there's like two clouds"
  },
  "2": {
    "start": 13.08,
    "end": 15.329,
    "transcript": "and they're like both like white with like a bit of gray"
  },
  "3": {
    "start": 15.89,
    "end": 17.369,
    "transcript": "like shaded in"
  },
  "4": {
    "start": 17.82,
    "end": 21.149,
    "transcript": "so for the toys store there's like two teddy bears in the front"
  },
  "5": {
    "start": 21.87,
    "end": 24.989,
    "transcript": "with like oh oh red massive red bows"
  },
  "6": {
    "start": 25.62,
    "end": 25.919,
    "transcript": "on"
  },
  "7": {
    "start": 28.92,
    "end": 31.109,
    "transcript": "oh wait which one has a red waistcoat red"
  },
  "8": {
    "start": 33.13037,
    "end": 34.65,
    "transcript": "okay yeah so that's not like"
  },
  "9": {
    "start": 36.939,
    "end": 46.409,
    "transcript": "uhm and this the sign says toys and it's got it's in like blue like semi circles like all around but then like a flu like a few light blue ones if you know what i mean"
  },
  "10": {
    "start": 47.39716,
    "end": 48.329,
    "transcript": "so yeah and then"
  },
  "11": {
    "start": 48.78,
    "end": 50.759,
    "transcript": "then next to it there's a pharmacy"
  },
  "12": {
    "start": 51.84,
    "end": 52.709,
    "transcript": "which says on like"
  },
  "13": {
    "start": 53.22,
    "end": 55.98,
    "transcript": "the sign on the left it says pillboxes on sale"
  },
  "14": {
    "start": 57.17,
    "end": 57.989,
    "transcript": "oh okay well"
  },
  "15": {
    "start": 58.43,
    "end": 60.089,
    "transcript": "and one of the doors is like a bit open"
  },
  "16": {
    "start": 61.05,
    "end": 63.929,
    "transcript": "and then it says pharmacy with like a red cross"
  },
  "17": {
    "start": 64.75399,
    "end": 69.089,
    "transcript": "and the sign is red and then on the sign on the right it says extra shine with extra"
  },
  "18": {
    "start": 70.53,
    "end": 71.839,
    "transcript": "pearl toothpaste"
  },
  "19": {
    "start": 73.09,
    "end": 74.419,
    "transcript": "ok so yeah"
  },
  "20": {
    "start": 76.24092,
    "end": 82.77,
    "transcript": "and then like in between this shop and the place your bet shop there's like three like birds eating like chips or something from the floor"
  },
  "21": {
    "start": 84.99,
    "end": 86.29,
    "transcript": "yeah with red wings"
  },
  "22": {
    "start": 86.52,
    "end": 86.829,
    "transcript": "red"
  },
  "23": {
    "start": 87.339,
    "end": 88.779,
    "transcript": "wings yeah ok"
  },
  "24": {
    "start": 89.25,
    "end": 93.23443,
    "transcript": "and uhm so there's a shop that says place your bets and then above it"
  },
  "25": {
    "start": 93.75,
    "end": 94.589,
    "transcript": "you haven't got that"
  },
  "26": {
    "start": 96.28,
    "end": 97.699,
    "transcript": "oh well there you are"
  },
  "27": {
    "start": 98.56,
    "end": 101.56,
    "transcript": "and there's one with like and it's got two birds above it like"
  },
  "28": {
    "start": 103.66,
    "end": 105.639,
    "transcript": "and so there's a guy that kinda looks like monopoly"
  },
  "29": {
    "start": 106.48,
    "end": 109.329,
    "transcript": "dude in it uh he's wearing a black suit and he's got like"
  },
  "30": {
    "start": 110.53,
    "end": 111.279,
    "transcript": "oh well there you are"
  },
  "31": {
    "start": 113.3,
    "end": 114.46,
    "transcript": "it's got like the door"
  },
  "32": {
    "start": 115.0,
    "end": 117.459,
    "transcript": "has got green like darker green handles on it"
  },
  "33": {
    "start": 118.66,
    "end": 119.649,
    "transcript": "okay so there's like a little"
  },
  "34": {
    "start": 121.69,
    "end": 123.619,
    "transcript": "no wait where does it say bet here"
  },
  "35": {
    "start": 126.55,
    "end": 126.90576,
    "transcript": "oh"
  },
  "36": {
    "start": 127.67292,
    "end": 129.319,
    "transcript": "oh mine says place your bets"
  },
  "37": {
    "start": 130.81,
    "end": 131.65,
    "transcript": "oh okay cool"
  },
  "38": {
    "start": 132.609,
    "end": 133.70834,
    "transcript": "uh wait"
  },
  "39": {
    "start": 134.42,
    "end": 136.809,
    "transcript": "wait how many have you gotten so far i've only got five"
  },
  "40": {
    "start": 139.7695,
    "end": 140.689,
    "transcript": "oh okay"
  },
  "41": {
    "start": 144.94,
    "end": 146.51,
    "transcript": "yeah the window at the top"
  },
  "42": {
    "start": 147.8,
    "end": 148.189,
    "transcript": "no"
  },
  "43": {
    "start": 150.709,
    "end": 151.04,
    "transcript": "ok"
  },
  "44": {
    "start": 152.39,
    "end": 154.72474,
    "transcript": "i think that's the one i thought you were talking about before"
  },
  "45": {
    "start": 155.54,
    "end": 158.269,
    "transcript": "okay so there's like a little pop up shop kind of thing"
  },
  "46": {
    "start": 158.57,
    "end": 162.399,
    "transcript": "next to it and it's and there's like a massive blue sign on the right like on the one of the walls"
  },
  "47": {
    "start": 163.19,
    "end": 163.79,
    "transcript": "and it's blue"
  },
  "48": {
    "start": 164.18,
    "end": 166.369,
    "transcript": "it says sell your secondhand goods"
  },
  "49": {
    "start": 169.04,
    "end": 169.29028,
    "transcript": "okay"
  },
  "50": {
    "start": 169.51,
    "end": 169.899,
    "transcript": "there are"
  },
  "51": {
    "start": 171.09,
    "end": 171.95,
    "transcript": "highlight wrong part"
  },
  "52": {
    "start": 172.17,
    "end": 172.649,
    "transcript": "okay yeah"
  },
  "53": {
    "start": 173.45,
    "end": 175.71,
    "transcript": "and it's got like three shelves in the window"
  },
  "54": {
    "start": 176.96,
    "end": 179.539,
    "transcript": "and it's got a blue a brown and brown rock on the top one"
  },
  "55": {
    "start": 179.85,
    "end": 183.859,
    "transcript": "a pink like a square thing and like a blue rock on the middle"
  },
  "56": {
    "start": 184.36934,
    "end": 184.519,
    "transcript": "and"
  },
  "57": {
    "start": 186.11,
    "end": 187.01,
    "transcript": "yeah like it's like"
  },
  "58": {
    "start": 187.49,
    "end": 187.729,
    "transcript": "green"
  },
  "59": {
    "start": 188.15,
    "end": 190.489,
    "transcript": "and then there's like on the bottom"
  },
  "60": {
    "start": 190.73,
    "end": 191.689,
    "transcript": "one there's like"
  },
  "61": {
    "start": 192.14,
    "end": 193.79,
    "transcript": "a red rock a red"
  },
  "62": {
    "start": 194.63,
    "end": 195.229,
    "transcript": "i don't know"
  },
  "63": {
    "start": 195.62,
    "end": 198.78008,
    "transcript": "a red cube and like a light green like square"
  },
  "64": {
    "start": 199.86,
    "end": 200.839,
    "transcript": "and then there's a cat"
  },
  "65": {
    "start": 201.44,
    "end": 203.09,
    "transcript": "sitting next to it like"
  },
  "66": {
    "start": 204.0,
    "end": 206.509,
    "transcript": "yeah mine's lying down like it looks like it's asleep"
  },
  "67": {
    "start": 206.8,
    "end": 207.649,
    "transcript": "and it's ginger"
  },
  "68": {
    "start": 208.80698,
    "end": 211.279,
    "transcript": "and its tail's just like there i guess"
  },
  "69": {
    "start": 211.71439,
    "end": 213.789,
    "transcript": "and there's a bench with nobody sitting on it"
  },
  "70": {
    "start": 214.85,
    "end": 220.29563,
    "transcript": "and it's like it's just just a bench and then there's like a lamppost with uhm"
  },
  "71": {
    "start": 221.3,
    "end": 223.309,
    "transcript": "nothing is happening on it it's just"
  },
  "72": {
    "start": 225.68,
    "end": 227.399,
    "transcript": "oh well that's not on mine"
  },
  "73": {
    "start": 228.009,
    "end": 229.14,
    "transcript": "ok"
  },
  "74": {
    "start": 229.58,
    "end": 230.2,
    "transcript": "so"
  },
  "75": {
    "start": 230.529,
    "end": 235.479,
    "transcript": "got that and then there's a lady walking past with some pink shoes and a grey like"
  },
  "76": {
    "start": 236.23,
    "end": 236.769,
    "transcript": "skirt"
  },
  "77": {
    "start": 239.14395,
    "end": 239.869,
    "transcript": "oh well"
  },
  "78": {
    "start": 240.59,
    "end": 241.639,
    "transcript": "what hand does she holding"
  },
  "79": {
    "start": 242.63,
    "end": 243.81,
    "transcript": "the back one or the front one"
  },
  "80": {
    "start": 244.35,
    "end": 244.689,
    "transcript": "okay"
  },
  "81": {
    "start": 245.29775,
    "end": 246.41,
    "transcript": "uhm uh and"
  },
  "82": {
    "start": 246.89,
    "end": 248.239,
    "transcript": "bird about to poop on her head"
  },
  "83": {
    "start": 255.62,
    "end": 256.94,
    "transcript": "i guess i'm not too sure"
  },
  "84": {
    "start": 257.36,
    "end": 258.349,
    "transcript": "one and then we'll see"
  },
  "85": {
    "start": 258.68,
    "end": 259.95,
    "transcript": "if we can't find another one"
  },
  "86": {
    "start": 260.339,
    "end": 262.25195,
    "transcript": "and there's a bird about to poop on her hair"
  },
  "87": {
    "start": 266.7,
    "end": 267.869,
    "transcript": "yeah is pooped but like"
  },
  "88": {
    "start": 268.12,
    "end": 268.95,
    "transcript": "it's like flying"
  },
  "89": {
    "start": 269.38,
    "end": 270.0,
    "transcript": "her head"
  },
  "90": {
    "start": 270.48,
    "end": 271.449,
    "transcript": "yeah ok"
  },
  "91": {
    "start": 272.29,
    "end": 275.52,
    "transcript": "and then on the sign on the other like the lamppost on other side of the road"
  },
  "92": {
    "start": 275.94,
    "end": 278.899,
    "transcript": "it says doctor and there's like an arrow pointing towards"
  },
  "93": {
    "start": 279.32,
    "end": 279.989,
    "transcript": "okay okay"
  },
  "94": {
    "start": 281.15,
    "end": 283.26,
    "transcript": "it's like uhm in the same place i guess as"
  },
  "95": {
    "start": 283.56,
    "end": 284.16,
    "transcript": "sign"
  },
  "96": {
    "start": 286.08,
    "end": 289.009,
    "transcript": "so yeah behind the the lamppost is a oh"
  },
  "97": {
    "start": 289.8,
    "end": 291.699,
    "transcript": "sign that says pete's pet shop"
  },
  "98": {
    "start": 294.23,
    "end": 296.959,
    "transcript": "okay so yeah uhm and it's like oh"
  },
  "99": {
    "start": 297.559,
    "end": 298.48,
    "transcript": "uhm uh"
  },
  "100": {
    "start": 298.95,
    "end": 302.059,
    "transcript": "window with four panels and it's like bright red on the inside"
  },
  "101": {
    "start": 302.78,
    "end": 304.489,
    "transcript": "and there's like a bird cage"
  },
  "102": {
    "start": 304.84,
    "end": 309.679,
    "transcript": "in one the bottom left and then above that is like a blue sign with some scribbles on it"
  },
  "103": {
    "start": 310.129,
    "end": 311.92,
    "transcript": "and then you can't see the other ones because it's hidden"
  },
  "104": {
    "start": 314.1,
    "end": 314.599,
    "transcript": "yeah like a"
  },
  "105": {
    "start": 315.12,
    "end": 317.119,
    "transcript": "thing and then on the door it says open"
  },
  "106": {
    "start": 318.15,
    "end": 319.949,
    "transcript": "and then below it there's like a girl"
  },
  "107": {
    "start": 321.27,
    "end": 324.119,
    "transcript": "with like a light green and dark green stripy dress"
  },
  "108": {
    "start": 326.63,
    "end": 327.159,
    "transcript": "yeah yeah"
  },
  "109": {
    "start": 330.9,
    "end": 334.82,
    "transcript": "it's like a i think it's like a letterbox for a cat with like an open sign on it"
  },
  "110": {
    "start": 335.64,
    "end": 336.449,
    "transcript": "i can't tell"
  },
  "111": {
    "start": 337.32,
    "end": 341.639,
    "transcript": "yeah and then the girls like pointing at the pet shop i guess it's her mum crossing the road"
  },
  "112": {
    "start": 342.0,
    "end": 345.26,
    "transcript": "and she's wearing like grey shoes and yeah that's it really"
  },
  "113": {
    "start": 345.69,
    "end": 348.599,
    "transcript": "and then there's a cafe next to it with like a picture of a pie"
  },
  "114": {
    "start": 349.3045,
    "end": 349.859,
    "transcript": "with like"
  },
  "115": {
    "start": 351.62,
    "end": 353.389,
    "transcript": "yeah and it's got like a red filling"
  },
  "116": {
    "start": 355.26,
    "end": 356.919,
    "transcript": "yeah wait where are the blueberries"
  },
  "117": {
    "start": 358.11247,
    "end": 358.889,
    "transcript": "no"
  },
  "118": {
    "start": 360.23,
    "end": 361.469,
    "transcript": "wait what do you mean no"
  },
  "119": {
    "start": 363.52,
    "end": 365.089,
    "transcript": "oh okay yeah i can see that"
  },
  "120": {
    "start": 366.069,
    "end": 373.559,
    "transcript": "uhm so yeah the cafe's like this little like shady thing i don't know what it's called it's white orange white orange white orange white orange"
  },
  "121": {
    "start": 374.08,
    "end": 374.529,
    "transcript": "and then"
  },
  "122": {
    "start": 375.4,
    "end": 376.09687,
    "transcript": "there's a"
  },
  "123": {
    "start": 376.57,
    "end": 379.179,
    "transcript": "panelled window on the left and the right of the door"
  },
  "124": {
    "start": 380.31,
    "end": 382.079,
    "transcript": "the one on the left is really like big"
  },
  "125": {
    "start": 382.78,
    "end": 387.669,
    "transcript": "there's like 16 panels on it well not you can see them like there would be 16"
  },
  "126": {
    "start": 388.09465,
    "end": 391.599,
    "transcript": "and then next to it it's like a four four four panelled door"
  },
  "127": {
    "start": 393.24137,
    "end": 395.13329,
    "transcript": "and then like a blue table"
  },
  "128": {
    "start": 395.53,
    "end": 401.299,
    "transcript": "with two chairs and a menu nothing like like it's just says menu on it nothing else"
  },
  "129": {
    "start": 402.98,
    "end": 405.649,
    "transcript": "there's two salt shakers and one pepper i guess"
  },
  "130": {
    "start": 406.45,
    "end": 408.409,
    "transcript": "and the table's like blue like"
  },
  "131": {
    "start": 409.37,
    "end": 411.339,
    "transcript": "wait what yeah yeah yeah they're yellow"
  },
  "132": {
    "start": 412.84,
    "end": 415.149,
    "transcript": "yeah wait the table and the chairs are blue"
  },
  "133": {
    "start": 415.8,
    "end": 419.88,
    "transcript": "how many we got one two three four five six seven eight nine ten eleven"
  },
  "134": {
    "start": 421.00505,
    "end": 425.529,
    "transcript": "uh i think we have 11 so there's three birds for you that are like eating stuff"
  },
  "135": {
    "start": 426.07,
    "end": 428.68864,
    "transcript": "the bird that's about to poop on this woman's head"
  },
  "136": {
    "start": 429.96,
    "end": 431.38921,
    "transcript": "yeah and it's like"
  },
  "137": {
    "start": 432.21,
    "end": 434.009,
    "transcript": "looking at her kind of it's kind of weird"
  },
  "138": {
    "start": 435.83553,
    "end": 436.689,
    "transcript": "and then um"
  },
  "139": {
    "start": 439.21,
    "end": 442.669,
    "transcript": "um so yeah the airplane oh just got like red wings"
  },
  "140": {
    "start": 443.87,
    "end": 444.399,
    "transcript": "um"
  },
  "141": {
    "start": 446.12,
    "end": 446.779,
    "transcript": "uh"
  },
  "142": {
    "start": 451.0,
    "end": 451.369,
    "transcript": "pink"
  },
  "143": {
    "start": 452.33,
    "end": 453.32,
    "transcript": "yeah like a real"
  },
  "144": {
    "start": 453.59,
    "end": 454.019,
    "transcript": "think"
  },
  "145": {
    "start": 454.55,
    "end": 457.999,
    "transcript": "the cat's just asleep it's got like you can only see three of its legs"
  },
  "146": {
    "start": 459.2,
    "end": 460.419,
    "transcript": "it's got whiskers"
  },
  "147": {
    "start": 461.1,
    "end": 461.439,
    "transcript": "um"
  },
  "148": {
    "start": 465.9,
    "end": 466.28,
    "transcript": "yeah like"
  },
  "149": {
    "start": 467.24,
    "end": 468.479,
    "transcript": "vest is like got like kind of"
  },
  "150": {
    "start": 468.75,
    "end": 469.699,
    "transcript": "faint stripes on it"
  },
  "151": {
    "start": 470.94,
    "end": 472.36837,
    "transcript": "so uhm"
  },
  "152": {
    "start": 472.86,
    "end": 474.1,
    "transcript": "yeah the birds"
  },
  "153": {
    "start": 474.97,
    "end": 475.519,
    "transcript": "there"
  },
  "154": {
    "start": 479.79,
    "end": 481.859,
    "transcript": "yeah and the one on the like little cat"
  },
  "155": {
    "start": 482.28,
    "end": 486.069,
    "transcript": "you know like the cat flap at the bottom of the pet shop has it got a sign on it"
  },
  "156": {
    "start": 486.96,
    "end": 487.829,
    "transcript": "like a red one"
  },
  "157": {
    "start": 488.73,
    "end": 490.229,
    "transcript": "and then the girl's pointing at it"
  },
  "158": {
    "start": 490.64,
    "end": 492.449,
    "transcript": "with one of her hands only though"
  },
  "159": {
    "start": 494.05,
    "end": 495.999,
    "transcript": "um oh so you know the cafe"
  },
  "160": {
    "start": 496.75,
    "end": 498.399,
    "transcript": "the door's got four panels"
  },
  "161": {
    "start": 499.15,
    "end": 500.889,
    "transcript": "and it's like brown and white striped"
  },
  "162": {
    "start": 501.72343,
    "end": 503.35063,
    "transcript": "the the front of the"
  },
  "163": {
    "start": 505.26,
    "end": 506.91,
    "transcript": "no no no the door isn't like the"
  },
  "164": {
    "start": 508.58,
    "end": 510.469,
    "transcript": "oh this is really difficult um"
  },
  "165": {
    "start": 511.41,
    "end": 513.06,
    "transcript": "so you know in front of the toy shop"
  },
  "166": {
    "start": 513.75,
    "end": 516.12,
    "transcript": "is there anything like there like in that area"
  },
  "167": {
    "start": 517.1341,
    "end": 518.019,
    "transcript": "hmm okay"
  },
  "168": {
    "start": 519.83,
    "end": 520.179,
    "transcript": "um"
  },
  "169": {
    "start": 521.19,
    "end": 521.819,
    "transcript": "so"
  },
  "170": {
    "start": 523.56,
    "end": 524.549,
    "transcript": "wait what is there"
  },
  "171": {
    "start": 525.24,
    "end": 527.279,
    "transcript": "so you know the place your bets thing"
  },
  "172": {
    "start": 528.44,
    "end": 530.029,
    "transcript": "so you know they have the lamppost"
  },
  "173": {
    "start": 530.46,
    "end": 530.789,
    "transcript": "and like"
  },
  "174": {
    "start": 531.57,
    "end": 534.029,
    "transcript": "no so sorry you know your the place your bets thing"
  },
  "175": {
    "start": 534.69,
    "end": 536.189,
    "transcript": "it's on like a little grey stand"
  },
  "176": {
    "start": 537.42,
    "end": 538.77412,
    "transcript": "so on like the second"
  },
  "177": {
    "start": 539.97,
    "end": 540.329,
    "transcript": "like"
  },
  "178": {
    "start": 540.78,
    "end": 541.83,
    "transcript": "so it's like kind"
  },
  "179": {
    "start": 542.51,
    "end": 545.249,
    "transcript": "so it's like divided up into like different like sections"
  },
  "180": {
    "start": 546.33768,
    "end": 547.14,
    "transcript": "is the second"
  },
  "181": {
    "start": 548.01,
    "end": 549.549,
    "transcript": "shaded in a bit grey"
  },
  "182": {
    "start": 550.89252,
    "end": 551.579,
    "transcript": "oh yeah"
  },
  "183": {
    "start": 552.28466,
    "end": 553.689,
    "transcript": "uhm uhm"
  },
  "184": {
    "start": 554.45902,
    "end": 557.46,
    "transcript": "so yeah the sign is blue for the sell your secondhand goods thing"
  },
  "185": {
    "start": 560.0,
    "end": 560.509,
    "transcript": "yeah"
  },
  "186": {
    "start": 566.06,
    "end": 568.769,
    "transcript": "uh yeah she is should we just do the thing where she's like"
  },
  "187": {
    "start": 569.46,
    "end": 572.85,
    "transcript": "got vare feet but also like okay let's just put"
  },
  "188": {
    "start": 573.99,
    "end": 575.0188,
    "transcript": "okay yup"
  },
  "189": {
    "start": 577.26,
    "end": 578.929,
    "transcript": "yeah hopefully we got that right"
  }
}