{
  "0": {
    "start": 10.62336,
    "end": 12.43874,
    "transcript": "okay right so"
  },
  "1": {
    "start": 13.24,
    "end": 16.029,
    "transcript": "top left corner we have a"
  },
  "2": {
    "start": 17.16,
    "end": 19.529,
    "transcript": "like a women under a woman under like a kind of"
  },
  "3": {
    "start": 20.18,
    "end": 20.999,
    "transcript": "what d'you call it like"
  },
  "4": {
    "start": 21.36,
    "end": 22.13,
    "transcript": "tent thingy"
  },
  "5": {
    "start": 23.12315,
    "end": 23.57535,
    "transcript": "uhm"
  },
  "6": {
    "start": 24.39,
    "end": 24.929,
    "transcript": "and"
  },
  "7": {
    "start": 25.59,
    "end": 26.489,
    "transcript": "there is"
  },
  "8": {
    "start": 28.1,
    "end": 33.41482,
    "transcript": "there's on on the left of the tent there's like two hanging sh- rings of shells"
  },
  "9": {
    "start": 34.16,
    "end": 36.169,
    "transcript": "and then there's one on the right as well"
  },
  "10": {
    "start": 38.73596,
    "end": 40.429,
    "transcript": "okay so i'll circle that"
  },
  "11": {
    "start": 41.46798,
    "end": 41.84774,
    "transcript": "uhm"
  },
  "12": {
    "start": 42.74775,
    "end": 47.969,
    "transcript": "uh so the woman has a she's in front of a table uhm she's wearing a green vest top"
  },
  "13": {
    "start": 48.66,
    "end": 49.469,
    "transcript": "and blue"
  },
  "14": {
    "start": 50.19,
    "end": 52.01739,
    "transcript": "whatever she's wearing under there uhm"
  },
  "15": {
    "start": 52.43667,
    "end": 53.618,
    "transcript": "and brown hair"
  },
  "16": {
    "start": 54.45,
    "end": 57.57472,
    "transcript": "and she has two tennis rackets on the left of the table"
  },
  "17": {
    "start": 58.38,
    "end": 59.579,
    "transcript": "and two pairs of"
  },
  "18": {
    "start": 59.85,
    "end": 63.79515,
    "transcript": "two there's a pair of socks uhm with an- anchors on them"
  },
  "19": {
    "start": 67.96,
    "end": 68.26,
    "transcript": "right"
  },
  "20": {
    "start": 68.71,
    "end": 69.99,
    "transcript": "okay we'll circle that then"
  },
  "21": {
    "start": 70.96,
    "end": 74.39084,
    "transcript": "and then below the table there's a box with tennis rackets"
  },
  "22": {
    "start": 78.45382,
    "end": 79.87407,
    "transcript": "oh right no we don't have that uh"
  },
  "23": {
    "start": 82.04,
    "end": 83.359,
    "transcript": "okay i'll circle that then"
  },
  "24": {
    "start": 83.96396,
    "end": 84.70498,
    "transcript": "cool"
  },
  "25": {
    "start": 85.29547,
    "end": 87.439,
    "transcript": "uhm so near the top of the picture"
  },
  "26": {
    "start": 88.34707,
    "end": 89.569,
    "transcript": "uh there's a"
  },
  "27": {
    "start": 90.20634,
    "end": 93.13982,
    "transcript": "i dunno if it's a man or a woman i can't tell but they're fishing"
  },
  "28": {
    "start": 93.40543,
    "end": 98.46,
    "transcript": "uhm black top red kind of reddy orange kind of s- whatever"
  },
  "29": {
    "start": 98.87367,
    "end": 101.609,
    "transcript": "uhm and a like a beige hat"
  },
  "30": {
    "start": 103.42892,
    "end": 105.71222,
    "transcript": "uhm and then where the fishing line"
  },
  "31": {
    "start": 106.23,
    "end": 108.41443,
    "transcript": "is going into the sea there's a shark to the right of it"
  },
  "32": {
    "start": 109.65,
    "end": 109.99326,
    "transcript": "right"
  },
  "33": {
    "start": 110.469,
    "end": 111.04034,
    "transcript": "uhm"
  },
  "34": {
    "start": 112.53,
    "end": 116.179,
    "transcript": "right so on on the beach below that there's a sand castle"
  },
  "35": {
    "start": 117.08149,
    "end": 117.53589,
    "transcript": "uh"
  },
  "36": {
    "start": 118.68,
    "end": 119.849,
    "transcript": "and on each"
  },
  "37": {
    "start": 120.45,
    "end": 121.30254,
    "transcript": "turret"
  },
  "38": {
    "start": 122.25084,
    "end": 123.989,
    "transcript": "uh so so from the from the"
  },
  "39": {
    "start": 124.7564,
    "end": 126.029,
    "transcript": "from like clockwise turret"
  },
  "40": {
    "start": 126.3,
    "end": 130.639,
    "transcript": "turret wise its uhm blue red like blue flag red flag blue flag"
  },
  "41": {
    "start": 131.81,
    "end": 132.379,
    "transcript": "you got that yeah"
  },
  "42": {
    "start": 133.14,
    "end": 136.699,
    "transcript": "okay and then slight to the right slightly above there's a"
  },
  "43": {
    "start": 137.2,
    "end": 137.929,
    "transcript": "like a red"
  },
  "44": {
    "start": 138.68,
    "end": 139.37115,
    "transcript": "bucket"
  },
  "45": {
    "start": 139.88,
    "end": 140.929,
    "transcript": "and a yellow spade"
  },
  "46": {
    "start": 142.06731,
    "end": 142.96293,
    "transcript": "hmm okay"
  },
  "47": {
    "start": 143.33,
    "end": 144.679,
    "transcript": "right so in the"
  },
  "48": {
    "start": 145.13,
    "end": 149.5172,
    "transcript": "top right hand corner of the picture there is a bunch of rocks"
  },
  "49": {
    "start": 150.41941,
    "end": 150.95502,
    "transcript": "uhm"
  },
  "50": {
    "start": 151.82,
    "end": 152.869,
    "transcript": "all but one"
  },
  "51": {
    "start": 153.28277,
    "end": 156.439,
    "transcript": "like all of them are dark and then there's one rock that's slightly lighter"
  },
  "52": {
    "start": 157.89,
    "end": 158.309,
    "transcript": "and then"
  },
  "53": {
    "start": 160.83,
    "end": 161.42512,
    "transcript": "yeah"
  },
  "54": {
    "start": 163.7,
    "end": 164.48861,
    "transcript": "yeah"
  },
  "55": {
    "start": 166.62555,
    "end": 167.69,
    "transcript": "yeah yeah that's it"
  },
  "56": {
    "start": 168.16,
    "end": 170.49118,
    "transcript": "there's a seagull sitting on top of the main rock"
  },
  "57": {
    "start": 172.18,
    "end": 172.469,
    "transcript": "okay"
  },
  "58": {
    "start": 173.76302,
    "end": 174.01107,
    "transcript": "right"
  },
  "59": {
    "start": 174.78319,
    "end": 175.24198,
    "transcript": "uhm"
  },
  "60": {
    "start": 178.43,
    "end": 179.09,
    "transcript": "it's blue"
  },
  "61": {
    "start": 180.76838,
    "end": 181.33692,
    "transcript": "cool"
  },
  "62": {
    "start": 181.88571,
    "end": 187.789,
    "transcript": "uh so below the rocks there's a rubbish bin and it's like full it's like almost overflowing"
  },
  "63": {
    "start": 191.30368,
    "end": 193.4198,
    "transcript": "oh no no okay circle that"
  },
  "64": {
    "start": 193.99,
    "end": 194.949,
    "transcript": "and it's blue as well"
  },
  "65": {
    "start": 196.27,
    "end": 197.239,
    "transcript": "okay circle the bin"
  },
  "66": {
    "start": 197.86,
    "end": 199.909,
    "transcript": "ne- so the right to the right of the bin there's a"
  },
  "67": {
    "start": 200.33,
    "end": 205.10975,
    "transcript": "white sign uh that says north beach with an arrow pointing to the right"
  },
  "68": {
    "start": 208.0695,
    "end": 208.419,
    "transcript": "okay"
  },
  "69": {
    "start": 209.05512,
    "end": 209.2439,
    "transcript": "right"
  },
  "70": {
    "start": 210.63,
    "end": 216.699,
    "transcript": "okay uh below that is a car like kind of like a red"
  },
  "71": {
    "start": 217.26,
    "end": 218.979,
    "transcript": "kind of beach vehicle i guess"
  },
  "72": {
    "start": 219.50683,
    "end": 219.9744,
    "transcript": "uhm"
  },
  "73": {
    "start": 220.72,
    "end": 222.62,
    "transcript": "it's red it's uh"
  },
  "74": {
    "start": 223.16684,
    "end": 225.4933,
    "transcript": "it's got a dog on it in the driver's seat"
  },
  "75": {
    "start": 226.19,
    "end": 226.519,
    "transcript": "yeah"
  },
  "76": {
    "start": 227.08,
    "end": 227.479,
    "transcript": "uh"
  },
  "77": {
    "start": 228.83,
    "end": 229.56399,
    "transcript": "no"
  },
  "78": {
    "start": 235.76923,
    "end": 237.789,
    "transcript": "uhm he's sitting on a blue chair"
  },
  "79": {
    "start": 241.11,
    "end": 245.6061,
    "transcript": "yeah yeah yeah same and then at the front of the car there's two men pushing it"
  },
  "80": {
    "start": 246.39,
    "end": 247.589,
    "transcript": "they're shouting push"
  },
  "81": {
    "start": 250.36,
    "end": 251.65,
    "transcript": "no so we'll circle that"
  },
  "82": {
    "start": 253.35964,
    "end": 253.73501,
    "transcript": "uhm"
  },
  "83": {
    "start": 254.32,
    "end": 259.00568,
    "transcript": "so the guy the guy nearest to us yeah he has a orange hat"
  },
  "84": {
    "start": 259.56,
    "end": 260.489,
    "transcript": "green tshirt"
  },
  "85": {
    "start": 261.45,
    "end": 262.289,
    "transcript": "black trousers"
  },
  "86": {
    "start": 263.1,
    "end": 263.91,
    "transcript": "and white shoes"
  },
  "87": {
    "start": 264.81,
    "end": 271.54496,
    "transcript": "the guy beh- uh the guy furthest away he has brown hair white tshirt blue trousers red shoes"
  },
  "88": {
    "start": 272.52,
    "end": 272.909,
    "transcript": "okay"
  },
  "89": {
    "start": 274.6,
    "end": 275.139,
    "transcript": "yeah yeah"
  },
  "90": {
    "start": 275.96705,
    "end": 281.17424,
    "transcript": "uhm and then at the to the back of the car there's a guy just with shorts on flip flops"
  },
  "91": {
    "start": 281.67,
    "end": 282.859,
    "transcript": "and he's shouting hey paul"
  },
  "92": {
    "start": 285.25443,
    "end": 287.419,
    "transcript": "right so if you ci- circle just to the right"
  },
  "93": {
    "start": 289.28943,
    "end": 290.80627,
    "transcript": "uhm and he's got a blue cap on"
  },
  "94": {
    "start": 292.26987,
    "end": 292.749,
    "transcript": "okay cool"
  },
  "95": {
    "start": 293.72,
    "end": 294.569,
    "transcript": "yeah and his"
  },
  "96": {
    "start": 294.77,
    "end": 296.539,
    "transcript": "his shorts are like orange and green"
  },
  "97": {
    "start": 297.5,
    "end": 298.279,
    "transcript": "yeah okay"
  },
  "98": {
    "start": 303.29724,
    "end": 304.179,
    "transcript": "yeah yeah that's it"
  },
  "99": {
    "start": 305.30799,
    "end": 308.809,
    "transcript": "uhm below the car there's three seagulls pecking the floor"
  },
  "100": {
    "start": 309.3642,
    "end": 311.36781,
    "transcript": "they're kind of like yeah uhm"
  },
  "101": {
    "start": 312.35562,
    "end": 313.25341,
    "transcript": "alright so"
  },
  "102": {
    "start": 314.359,
    "end": 314.839,
    "transcript": "to the"
  },
  "103": {
    "start": 315.26,
    "end": 320.379,
    "transcript": "so bottom central there's a women with a like an inflatable ring"
  },
  "104": {
    "start": 321.44,
    "end": 322.23,
    "transcript": "it's pink"
  },
  "105": {
    "start": 323.67,
    "end": 326.579,
    "transcript": "and she's got blonde hair and like a green bikini on"
  },
  "106": {
    "start": 327.80947,
    "end": 328.279,
    "transcript": "okay"
  },
  "107": {
    "start": 332.6,
    "end": 332.899,
    "transcript": "yep"
  },
  "108": {
    "start": 333.3,
    "end": 333.57936,
    "transcript": "yep"
  },
  "109": {
    "start": 334.3718,
    "end": 335.659,
    "transcript": "uhm so"
  },
  "110": {
    "start": 336.35,
    "end": 338.8868,
    "transcript": "to the left there is a taxi"
  },
  "111": {
    "start": 339.7749,
    "end": 341.959,
    "transcript": "uhm it's got like an orange stripe on the bonnet"
  },
  "112": {
    "start": 343.47901,
    "end": 346.00942,
    "transcript": "uhm and then yeah obviously yellow lights at the front"
  },
  "113": {
    "start": 346.61,
    "end": 349.609,
    "transcript": "on the number plate it says tax 1"
  },
  "114": {
    "start": 350.73809,
    "end": 352.179,
    "transcript": "okay gray wheels"
  },
  "115": {
    "start": 353.85207,
    "end": 355.479,
    "transcript": "uhm the doors are black"
  },
  "116": {
    "start": 356.98798,
    "end": 360.489,
    "transcript": "uhm and then the taxi sign on the top of is in orange with white writing"
  },
  "117": {
    "start": 363.57,
    "end": 364.54415,
    "transcript": "yep uhm"
  },
  "118": {
    "start": 365.08,
    "end": 365.919,
    "transcript": "and then the"
  },
  "119": {
    "start": 366.81134,
    "end": 368.829,
    "transcript": "the back i can't remember what you call it the opposite to the bonnet"
  },
  "120": {
    "start": 369.5,
    "end": 372.099,
    "transcript": "the boot that's the one uh that's orange as well"
  },
  "121": {
    "start": 374.29,
    "end": 376.00307,
    "transcript": "it is white yeah yeah"
  },
  "122": {
    "start": 376.27966,
    "end": 376.61332,
    "transcript": "uh"
  },
  "123": {
    "start": 377.78807,
    "end": 378.909,
    "transcript": "yeah yeah yeah yeah"
  },
  "124": {
    "start": 380.91392,
    "end": 381.12026,
    "transcript": "yeah"
  },
  "125": {
    "start": 384.28,
    "end": 386.46448,
    "transcript": "no it doesn't okay i'll"
  },
  "126": {
    "start": 388.12,
    "end": 388.329,
    "transcript": "yeah"
  },
  "127": {
    "start": 389.38,
    "end": 390.079,
    "transcript": "cool circled"
  },
  "128": {
    "start": 390.54944,
    "end": 390.94457,
    "transcript": "uhm"
  },
  "129": {
    "start": 392.15,
    "end": 397.179,
    "transcript": "right in the middle of the beach there's a sign that says one night only love shack"
  },
  "130": {
    "start": 401.45,
    "end": 403.02763,
    "transcript": "okay i'll circle that and it's green"
  },
  "131": {
    "start": 405.25842,
    "end": 406.959,
    "transcript": "okay uhm so"
  },
  "132": {
    "start": 407.78,
    "end": 411.159,
    "transcript": "central left of the picture there is a"
  },
  "133": {
    "start": 411.58,
    "end": 413.279,
    "transcript": "kind of like pop up shop thing"
  },
  "134": {
    "start": 413.78174,
    "end": 415.09982,
    "transcript": "it says smoothies on it"
  },
  "135": {
    "start": 416.18203,
    "end": 418.549,
    "transcript": "uhm at the bottom of it it has peaches"
  },
  "136": {
    "start": 419.80017,
    "end": 424.6,
    "transcript": "uhm with two two pictures of peaches one of which is chopped in half you see the inside of it"
  },
  "137": {
    "start": 425.44287,
    "end": 425.98507,
    "transcript": "uhm"
  },
  "138": {
    "start": 426.86,
    "end": 427.82019,
    "transcript": "and then on the"
  },
  "139": {
    "start": 428.59288,
    "end": 431.829,
    "transcript": "the s- the counter there's like a smoothie blender"
  },
  "140": {
    "start": 436.24,
    "end": 437.889,
    "transcript": "no i don't have that which side"
  },
  "141": {
    "start": 439.64,
    "end": 439.879,
    "transcript": "right"
  },
  "142": {
    "start": 440.75,
    "end": 441.049,
    "transcript": "there"
  },
  "143": {
    "start": 441.61,
    "end": 443.929,
    "transcript": "uhm the side of the shop is green"
  },
  "144": {
    "start": 445.27,
    "end": 447.31,
    "transcript": "the inside of the shop is green as well"
  },
  "145": {
    "start": 448.24,
    "end": 450.729,
    "transcript": "with like floor like four black squares"
  },
  "146": {
    "start": 452.02444,
    "end": 455.15159,
    "transcript": "yeah and at the top like yeah yeah that's it uhm"
  },
  "147": {
    "start": 455.74647,
    "end": 458.009,
    "transcript": "right that's about it uhm"
  },
  "148": {
    "start": 459.0,
    "end": 459.849,
    "transcript": "yeah yeah"
  },
  "149": {
    "start": 463.63648,
    "end": 463.86478,
    "transcript": "yeah"
  },
  "150": {
    "start": 464.48381,
    "end": 464.91186,
    "transcript": "yeah yeah"
  },
  "151": {
    "start": 465.34,
    "end": 472.029,
    "transcript": "okay right so how many have we got one two three four five six seven eight nine 10 so we need two more"
  },
  "152": {
    "start": 472.23,
    "end": 472.839,
    "transcript": "differences"
  },
  "153": {
    "start": 474.95728,
    "end": 475.55436,
    "transcript": "yeah"
  },
  "154": {
    "start": 478.03668,
    "end": 478.61839,
    "transcript": "uhuh"
  },
  "155": {
    "start": 482.27,
    "end": 483.43102,
    "transcript": "yeah yeah"
  },
  "156": {
    "start": 487.32,
    "end": 489.45224,
    "transcript": "yeah only only on three corners though"
  },
  "157": {
    "start": 490.74,
    "end": 491.77,
    "transcript": "yeah okay"
  },
  "158": {
    "start": 495.2,
    "end": 496.389,
    "transcript": "yeah and"
  },
  "159": {
    "start": 496.79,
    "end": 499.849,
    "transcript": "one's one side of the table has like a"
  },
  "160": {
    "start": 500.63,
    "end": 504.199,
    "transcript": "another kind of pole like connecting the legs if y'know what i mean on the right"
  },
  "161": {
    "start": 505.16751,
    "end": 505.97532,
    "transcript": "but not on the left"
  },
  "162": {
    "start": 509.53,
    "end": 510.039,
    "transcript": "corner"
  },
  "163": {
    "start": 510.91,
    "end": 512.979,
    "transcript": "yeah yeah got that yeah so that's"
  },
  "164": {
    "start": 513.29,
    "end": 513.659,
    "transcript": "same"
  },
  "165": {
    "start": 515.92603,
    "end": 516.71,
    "transcript": "yeah yeah"
  },
  "166": {
    "start": 517.15273,
    "end": 518.44,
    "transcript": "she looks pretty happy yeah"
  },
  "167": {
    "start": 519.02958,
    "end": 519.72322,
    "transcript": "uh"
  },
  "168": {
    "start": 521.02,
    "end": 524.74,
    "transcript": "what have you got anything else like right in the middle of the beach because i haven't got anything there"
  },
  "169": {
    "start": 526.21018,
    "end": 526.64262,
    "transcript": "uh"
  },
  "170": {
    "start": 531.97,
    "end": 532.749,
    "transcript": "yeah"
  },
  "171": {
    "start": 533.65,
    "end": 535.28209,
    "transcript": "yeah yeah yeah it's the same"
  },
  "172": {
    "start": 535.78,
    "end": 537.4302,
    "transcript": "yeah yeah the same"
  },
  "173": {
    "start": 539.66,
    "end": 540.019,
    "transcript": "yeah"
  },
  "174": {
    "start": 540.87453,
    "end": 541.24112,
    "transcript": "yeah"
  },
  "175": {
    "start": 543.35,
    "end": 543.799,
    "transcript": "yeah"
  },
  "176": {
    "start": 545.37,
    "end": 545.89,
    "transcript": "yeah"
  },
  "177": {
    "start": 546.31515,
    "end": 546.989,
    "transcript": "uhm"
  },
  "178": {
    "start": 548.18,
    "end": 549.929,
    "transcript": "what else it could be is the dog"
  },
  "179": {
    "start": 550.35,
    "end": 553.64398,
    "transcript": "has the dog got its mouth open because it's no same in mine uhm"
  },
  "180": {
    "start": 558.6,
    "end": 559.74898,
    "transcript": "pink chair there we"
  },
  "181": {
    "start": 560.33854,
    "end": 560.549,
    "transcript": "but"
  },
  "182": {
    "start": 561.06,
    "end": 562.649,
    "transcript": "so it hasn't got a blue chair underneath it"
  },
  "183": {
    "start": 566.10641,
    "end": 567.349,
    "transcript": "okay that's one there"
  },
  "184": {
    "start": 568.38,
    "end": 569.579,
    "transcript": "thing is it's hard to"
  },
  "185": {
    "start": 570.4,
    "end": 570.91028,
    "transcript": "circle"
  },
  "186": {
    "start": 572.889,
    "end": 575.959,
    "transcript": "oh apparent- oh apparently we've already spotted 12 differences what"
  },
  "187": {
    "start": 577.28,
    "end": 580.319,
    "transcript": "1 2 3 4 5 6 7 8 9 10"
  },
  "188": {
    "start": 581.58,
    "end": 583.30961,
    "transcript": "the dog must be two differences then alright"
  }
}