{
  "0": {
    "start": 15.18838,
    "end": 15.63344,
    "transcript": "yeah"
  },
  "1": {
    "start": 16.25983,
    "end": 17.159,
    "transcript": "s- yeah"
  },
  "2": {
    "start": 17.79,
    "end": 19.54442,
    "transcript": "yeah same"
  },
  "3": {
    "start": 23.1,
    "end": 23.369,
    "transcript": "yeah"
  },
  "4": {
    "start": 23.64,
    "end": 25.86765,
    "transcript": "does it actually say the word shop"
  },
  "5": {
    "start": 27.08,
    "end": 29.97173,
    "transcript": "yeah and has it got a an image on it"
  },
  "6": {
    "start": 33.67143,
    "end": 36.569,
    "transcript": "ok no but on the sign that says city pharmacy is there anything"
  },
  "7": {
    "start": 37.41406,
    "end": 38.759,
    "transcript": "ok mine's got two"
  },
  "8": {
    "start": 39.36,
    "end": 40.799,
    "transcript": "sort of tablets"
  },
  "9": {
    "start": 41.31067,
    "end": 42.56782,
    "transcript": "a- aspirins or something"
  },
  "10": {
    "start": 42.81,
    "end": 43.019,
    "transcript": "yeah"
  },
  "11": {
    "start": 44.25,
    "end": 45.89279,
    "transcript": "on on the actual city yeah"
  },
  "12": {
    "start": 48.72,
    "end": 49.1,
    "transcript": "yeah"
  },
  "13": {
    "start": 49.72,
    "end": 51.549,
    "transcript": "where wh- is the door on the right or the left"
  },
  "14": {
    "start": 54.91,
    "end": 55.149,
    "transcript": "yeah"
  },
  "15": {
    "start": 55.66,
    "end": 55.829,
    "transcript": "yeah"
  },
  "16": {
    "start": 58.49,
    "end": 59.79516,
    "transcript": "oh yeah yeah yeah yeah"
  },
  "17": {
    "start": 64.02,
    "end": 64.299,
    "transcript": "yeah"
  },
  "18": {
    "start": 65.05663,
    "end": 65.36276,
    "transcript": "yeah"
  },
  "19": {
    "start": 65.58883,
    "end": 65.779,
    "transcript": "yeah"
  },
  "20": {
    "start": 67.92,
    "end": 69.899,
    "transcript": "yeah with a picture of lips"
  },
  "21": {
    "start": 70.44472,
    "end": 70.6802,
    "transcript": "yeah"
  },
  "22": {
    "start": 71.52405,
    "end": 71.69125,
    "transcript": "yeah"
  },
  "23": {
    "start": 77.09987,
    "end": 77.38245,
    "transcript": "yeah"
  },
  "24": {
    "start": 80.5,
    "end": 80.799,
    "transcript": "yeah"
  },
  "25": {
    "start": 85.73,
    "end": 86.66388,
    "transcript": "how many"
  },
  "26": {
    "start": 88.28,
    "end": 88.53,
    "transcript": "yeah"
  },
  "27": {
    "start": 89.19,
    "end": 91.739,
    "transcript": "it just just the little ones or is there a big one as well"
  },
  "28": {
    "start": 92.71,
    "end": 94.5,
    "transcript": "okay i've got a big pie as well"
  },
  "29": {
    "start": 99.69,
    "end": 100.069,
    "transcript": "yeah"
  },
  "30": {
    "start": 101.88017,
    "end": 102.44881,
    "transcript": "<lg>"
  },
  "31": {
    "start": 106.66,
    "end": 106.96,
    "transcript": "yeah"
  },
  "32": {
    "start": 109.72,
    "end": 112.03636,
    "transcript": "yeah what color are his clothes"
  },
  "33": {
    "start": 113.13631,
    "end": 113.46128,
    "transcript": "yeah"
  },
  "34": {
    "start": 114.43,
    "end": 115.71186,
    "transcript": "yeah same"
  },
  "35": {
    "start": 117.63577,
    "end": 118.20499,
    "transcript": "yeah"
  },
  "36": {
    "start": 120.9807,
    "end": 121.16203,
    "transcript": "yeah"
  },
  "37": {
    "start": 126.35,
    "end": 127.879,
    "transcript": "okay mine's just toy shop"
  },
  "38": {
    "start": 131.09363,
    "end": 131.35737,
    "transcript": "yeah"
  },
  "39": {
    "start": 134.9,
    "end": 135.60393,
    "transcript": "yeah"
  },
  "40": {
    "start": 136.94,
    "end": 137.54,
    "transcript": "yeah yeah"
  },
  "41": {
    "start": 139.84,
    "end": 141.799,
    "transcript": "yeah two smaller and one bigger"
  },
  "42": {
    "start": 142.28,
    "end": 142.549,
    "transcript": "yeah"
  },
  "43": {
    "start": 145.65,
    "end": 148.009,
    "transcript": "okay we've just got uh i've just got a large one"
  },
  "44": {
    "start": 150.88598,
    "end": 151.14972,
    "transcript": "yup"
  },
  "45": {
    "start": 152.62467,
    "end": 153.2699,
    "transcript": "yup"
  },
  "46": {
    "start": 158.06422,
    "end": 158.3727,
    "transcript": "yeah"
  },
  "47": {
    "start": 161.61699,
    "end": 161.89251,
    "transcript": "yup"
  },
  "48": {
    "start": 163.15942,
    "end": 163.39725,
    "transcript": "yup"
  },
  "49": {
    "start": 165.94,
    "end": 166.359,
    "transcript": "yeah"
  },
  "50": {
    "start": 166.57,
    "end": 167.32,
    "transcript": "yeah yeah"
  },
  "51": {
    "start": 167.99,
    "end": 168.369,
    "transcript": "colour"
  },
  "52": {
    "start": 169.95651,
    "end": 170.23439,
    "transcript": "yeah"
  },
  "53": {
    "start": 177.24,
    "end": 177.609,
    "transcript": "yeah"
  },
  "54": {
    "start": 178.61182,
    "end": 178.82612,
    "transcript": "yeah"
  },
  "55": {
    "start": 179.32,
    "end": 179.939,
    "transcript": "yeah yeah"
  },
  "56": {
    "start": 181.33,
    "end": 183.039,
    "transcript": "yeah eh what kind of door is it is it"
  },
  "57": {
    "start": 185.91558,
    "end": 186.16284,
    "transcript": "yeah"
  },
  "58": {
    "start": 186.58907,
    "end": 186.899,
    "transcript": "yeah yeah"
  },
  "59": {
    "start": 188.01846,
    "end": 188.25865,
    "transcript": "yeah"
  },
  "60": {
    "start": 192.06,
    "end": 192.359,
    "transcript": "oh"
  },
  "61": {
    "start": 192.96,
    "end": 197.579,
    "transcript": "on the right no no you well you can't see what the book says on my one"
  },
  "62": {
    "start": 200.29,
    "end": 200.579,
    "transcript": "no"
  },
  "63": {
    "start": 201.79,
    "end": 202.39088,
    "transcript": "no"
  },
  "64": {
    "start": 206.34309,
    "end": 210.57,
    "transcript": "and is there the the is there a another signpost right in front of that bookstore"
  },
  "65": {
    "start": 211.62,
    "end": 211.819,
    "transcript": "yeah"
  },
  "66": {
    "start": 213.42,
    "end": 215.489,
    "transcript": "okay mine says next left for pet centre"
  },
  "67": {
    "start": 215.75,
    "end": 216.089,
    "transcript": "so"
  },
  "68": {
    "start": 216.54,
    "end": 217.259,
    "transcript": "that's a difference"
  },
  "69": {
    "start": 218.36374,
    "end": 218.56861,
    "transcript": "yeah"
  },
  "70": {
    "start": 222.60614,
    "end": 223.00647,
    "transcript": "uhuh"
  },
  "71": {
    "start": 224.63,
    "end": 225.919,
    "transcript": "mine's see you later bill"
  },
  "72": {
    "start": 229.46,
    "end": 229.779,
    "transcript": "yeah"
  },
  "73": {
    "start": 230.33,
    "end": 230.839,
    "transcript": "and"
  },
  "74": {
    "start": 231.6,
    "end": 234.76168,
    "transcript": "yellowy orange shoes and what colour hair"
  },
  "75": {
    "start": 235.71,
    "end": 236.069,
    "transcript": "yeah"
  },
  "76": {
    "start": 236.73,
    "end": 238.099,
    "transcript": "yeah blond or ginger yeah"
  },
  "77": {
    "start": 238.33,
    "end": 238.529,
    "transcript": "yeah"
  },
  "78": {
    "start": 239.73,
    "end": 240.08114,
    "transcript": "yeah"
  },
  "79": {
    "start": 244.15,
    "end": 247.1414,
    "transcript": "red with a kind of a pinky interior"
  },
  "80": {
    "start": 248.04801,
    "end": 248.38476,
    "transcript": "yeah"
  },
  "81": {
    "start": 248.75177,
    "end": 249.599,
    "transcript": "grey wheels"
  },
  "82": {
    "start": 250.39,
    "end": 251.88013,
    "transcript": "yeah uhm"
  },
  "83": {
    "start": 252.48532,
    "end": 252.759,
    "transcript": "yeah"
  },
  "84": {
    "start": 253.88,
    "end": 256.72892,
    "transcript": "yeah uh grey handle"
  },
  "85": {
    "start": 257.66376,
    "end": 259.609,
    "transcript": "uh black uh bumper"
  },
  "86": {
    "start": 260.98,
    "end": 261.77112,
    "transcript": "at the front"
  },
  "87": {
    "start": 262.319,
    "end": 263.90986,
    "transcript": "yeah can't see anything there"
  },
  "88": {
    "start": 266.32,
    "end": 266.649,
    "transcript": "yeah"
  },
  "89": {
    "start": 267.23394,
    "end": 267.46,
    "transcript": "yeah"
  },
  "90": {
    "start": 273.1,
    "end": 275.319,
    "transcript": "yeah dark yeah dark blue yeah i guess"
  },
  "91": {
    "start": 276.22,
    "end": 277.31393,
    "transcript": "royal blue yeah"
  },
  "92": {
    "start": 281.7,
    "end": 281.98,
    "transcript": "yeah"
  },
  "93": {
    "start": 282.52,
    "end": 283.639,
    "transcript": "and what color hair"
  },
  "94": {
    "start": 284.58,
    "end": 284.849,
    "transcript": "yeah"
  },
  "95": {
    "start": 286.71,
    "end": 288.739,
    "transcript": "yeah and shoes does she have shoes on"
  },
  "96": {
    "start": 289.93967,
    "end": 291.279,
    "transcript": "oh mine doesn't have shoes"
  },
  "97": {
    "start": 297.80437,
    "end": 298.61444,
    "transcript": "yeah"
  },
  "98": {
    "start": 299.28,
    "end": 300.539,
    "transcript": "which has is"
  },
  "99": {
    "start": 301.22237,
    "end": 303.419,
    "transcript": "four five uh what the sign is purplely yeah"
  },
  "100": {
    "start": 303.93,
    "end": 307.739,
    "transcript": "yeah light very pale lilacy bluey yeah and"
  },
  "101": {
    "start": 308.35,
    "end": 309.85,
    "transcript": "it says science fair yeah"
  },
  "102": {
    "start": 311.16,
    "end": 313.879,
    "transcript": "and the fair is spelt f a i yeah"
  },
  "103": {
    "start": 314.94227,
    "end": 316.79021,
    "transcript": "yeah and it's got underneath it"
  },
  "104": {
    "start": 317.759,
    "end": 319.179,
    "transcript": "oh right mine's got kind of"
  },
  "105": {
    "start": 319.9,
    "end": 322.41074,
    "transcript": "scientific amoeba blobs"
  },
  "106": {
    "start": 323.08,
    "end": 323.469,
    "transcript": "so"
  },
  "107": {
    "start": 323.86,
    "end": 324.039,
    "transcript": "yeah"
  },
  "108": {
    "start": 326.8,
    "end": 328.139,
    "transcript": "yeah not happy"
  },
  "109": {
    "start": 328.51,
    "end": 328.839,
    "transcript": "yeah"
  },
  "110": {
    "start": 329.62,
    "end": 329.949,
    "transcript": "yeah"
  },
  "111": {
    "start": 331.48,
    "end": 334.32,
    "transcript": "oh no she's got a yellow uhm trouser suit"
  },
  "112": {
    "start": 334.859,
    "end": 336.55,
    "transcript": "oh no not trouser suit sorry skirt suit"
  },
  "113": {
    "start": 337.39,
    "end": 337.959,
    "transcript": "so actually"
  },
  "114": {
    "start": 338.71,
    "end": 344.469,
    "transcript": "so that's a different colour and a different clothes i don't know if that't a two maybe it't just one for that"
  },
  "115": {
    "start": 345.2924,
    "end": 345.53731,
    "transcript": "yeah"
  },
  "116": {
    "start": 345.79,
    "end": 347.449,
    "transcript": "hows her does she have a bag"
  },
  "117": {
    "start": 348.82,
    "end": 349.59671,
    "transcript": "yeah"
  },
  "118": {
    "start": 349.83,
    "end": 350.789,
    "transcript": "shoes"
  },
  "119": {
    "start": 351.24,
    "end": 353.999,
    "transcript": "yeah yeah oh satchel like over her shoulder"
  },
  "120": {
    "start": 354.95589,
    "end": 356.179,
    "transcript": "no in her hand yeah"
  },
  "121": {
    "start": 359.23,
    "end": 361.579,
    "transcript": "pink pink i say pale pink yeah"
  },
  "122": {
    "start": 363.33,
    "end": 364.829,
    "transcript": "yeah exactly yeah yeah"
  },
  "123": {
    "start": 366.36,
    "end": 366.999,
    "transcript": "yeah"
  },
  "124": {
    "start": 367.2,
    "end": 368.369,
    "transcript": "and whats her hair doing"
  },
  "125": {
    "start": 369.36633,
    "end": 370.09453,
    "transcript": "yeah"
  },
  "126": {
    "start": 371.86,
    "end": 373.5758,
    "transcript": "yeah she's heading there"
  },
  "127": {
    "start": 374.89,
    "end": 375.46,
    "transcript": "yeah"
  },
  "128": {
    "start": 375.85,
    "end": 376.389,
    "transcript": "what colour"
  },
  "129": {
    "start": 378.95,
    "end": 380.089,
    "transcript": "yeah and what's he doing"
  },
  "130": {
    "start": 380.72,
    "end": 381.349,
    "transcript": "yeah same"
  },
  "131": {
    "start": 383.76,
    "end": 384.039,
    "transcript": "yeah"
  },
  "132": {
    "start": 384.99829,
    "end": 386.839,
    "transcript": "oh mine says leisure leisure park"
  },
  "133": {
    "start": 389.74,
    "end": 390.929,
    "transcript": "right shall we count"
  },
  "134": {
    "start": 392.47,
    "end": 393.71,
    "transcript": "three three"
  },
  "135": {
    "start": 396.98799,
    "end": 397.609,
    "transcript": "10"
  },
  "136": {
    "start": 398.45,
    "end": 399.259,
    "transcript": "i've got 10"
  },
  "137": {
    "start": 406.69,
    "end": 410.02883,
    "transcript": "10 and no 11 sorry i've got 11 <lg>"
  },
  "138": {
    "start": 410.84709,
    "end": 412.689,
    "transcript": "okay 11 right so what"
  },
  "139": {
    "start": 413.17,
    "end": 414.28,
    "transcript": "could we be missing"
  },
  "140": {
    "start": 414.61,
    "end": 417.399,
    "transcript": "what colour is the saddle on the girl's bike"
  },
  "141": {
    "start": 418.94,
    "end": 420.539,
    "transcript": "yeah well reddy orange yeah"
  },
  "142": {
    "start": 421.59031,
    "end": 422.0236,
    "transcript": "yeah"
  },
  "143": {
    "start": 422.49928,
    "end": 426.6,
    "transcript": "uhm oh you know the guy who's saying whatever see you later bill"
  },
  "144": {
    "start": 426.83,
    "end": 427.099,
    "transcript": "yeah"
  },
  "145": {
    "start": 427.6156,
    "end": 429.679,
    "transcript": "is he what's he doing with his arms"
  },
  "146": {
    "start": 430.50523,
    "end": 430.929,
    "transcript": "okay"
  },
  "147": {
    "start": 432.23979,
    "end": 434.40389,
    "transcript": "yeah left arms up yeah"
  },
  "148": {
    "start": 437.84,
    "end": 438.4747,
    "transcript": "yeah"
  },
  "149": {
    "start": 440.36,
    "end": 441.009,
    "transcript": "yeah"
  },
  "150": {
    "start": 441.26,
    "end": 441.54,
    "transcript": "yeah"
  },
  "151": {
    "start": 442.19,
    "end": 443.679,
    "transcript": "that's also turning left yeah"
  },
  "152": {
    "start": 447.12,
    "end": 447.419,
    "transcript": "yeah"
  },
  "153": {
    "start": 447.65,
    "end": 447.909,
    "transcript": "yeah"
  },
  "154": {
    "start": 451.769,
    "end": 455.659,
    "transcript": "the the toy shop uh above the where where it says toy shop above that"
  },
  "155": {
    "start": 455.86,
    "end": 458.769,
    "transcript": "that sign is there two stars on this on the sign"
  },
  "156": {
    "start": 458.99,
    "end": 459.7,
    "transcript": "yeah okay"
  },
  "157": {
    "start": 461.28261,
    "end": 462.13742,
    "transcript": "uhm"
  },
  "158": {
    "start": 463.60797,
    "end": 464.41332,
    "transcript": "uhh"
  },
  "159": {
    "start": 467.53,
    "end": 468.339,
    "transcript": "yeah that seems a big"
  },
  "160": {
    "start": 468.85,
    "end": 470.919,
    "transcript": "blob of nothing there with nothing"
  },
  "161": {
    "start": 471.99,
    "end": 475.259,
    "transcript": "is oh is it is it uh just a two door like is it"
  },
  "162": {
    "start": 475.54,
    "end": 476.359,
    "transcript": "two doors yeah"
  },
  "163": {
    "start": 479.81727,
    "end": 480.139,
    "transcript": "oh"
  },
  "164": {
    "start": 481.25,
    "end": 483.249,
    "transcript": "yeah it's driving to the left yeah"
  },
  "165": {
    "start": 484.04,
    "end": 484.459,
    "transcript": "yeah"
  },
  "166": {
    "start": 484.73,
    "end": 486.229,
    "transcript": "yeah exactly yeah"
  },
  "167": {
    "start": 486.98561,
    "end": 494.359,
    "transcript": "uhm hmm oh you know in the the butcher's shop where the pies are is there is does is there a sign that says pies"
  },
  "168": {
    "start": 494.89,
    "end": 495.82876,
    "transcript": "okay"
  },
  "169": {
    "start": 497.12741,
    "end": 498.17767,
    "transcript": "uhm"
  },
  "170": {
    "start": 502.29912,
    "end": 503.39648,
    "transcript": "uh"
  },
  "171": {
    "start": 504.56,
    "end": 506.119,
    "transcript": "and in the book shop the"
  },
  "172": {
    "start": 506.9,
    "end": 510.809,
    "transcript": "the pink thing that's on the left in window is a rectangle"
  },
  "173": {
    "start": 511.79,
    "end": 514.219,
    "transcript": "yeah and it doesn't you it doesn't say on it"
  },
  "174": {
    "start": 515.75,
    "end": 518.31225,
    "transcript": "some sort of squiggles but yeah yeah"
  },
  "175": {
    "start": 519.96408,
    "end": 520.97,
    "transcript": "yeah yeah yeah"
  },
  "176": {
    "start": 521.74,
    "end": 524.099,
    "transcript": "what color is that door on the bookshop"
  },
  "177": {
    "start": 526.22,
    "end": 528.21,
    "transcript": "yeah mustardy sort of yeah"
  },
  "178": {
    "start": 530.29252,
    "end": 530.76585,
    "transcript": "uhh"
  },
  "179": {
    "start": 532.45,
    "end": 536.82677,
    "transcript": "yeah that's the bit that we've got that different because the books what colour's the book"
  },
  "180": {
    "start": 537.38016,
    "end": 537.929,
    "transcript": "yeah same"
  },
  "181": {
    "start": 538.54,
    "end": 544.62,
    "transcript": "it's just the wording that's different uhm the s- the sun that's up in the on the left hand corner is"
  },
  "182": {
    "start": 545.38,
    "end": 547.499,
    "transcript": "the dots around it is just dots not"
  },
  "183": {
    "start": 548.04,
    "end": 548.369,
    "transcript": "yeah"
  },
  "184": {
    "start": 549.59,
    "end": 549.889,
    "transcript": "yeah"
  },
  "185": {
    "start": 551.03,
    "end": 552.309,
    "transcript": "yeah yeah yeah yeah"
  },
  "186": {
    "start": 553.38724,
    "end": 554.1667,
    "transcript": "uhm"
  },
  "187": {
    "start": 559.45,
    "end": 561.819,
    "transcript": "yeah yeah two bits of sludgy grey yeah"
  },
  "188": {
    "start": 562.26538,
    "end": 562.71,
    "transcript": "uhm"
  },
  "189": {
    "start": 564.16744,
    "end": 564.78206,
    "transcript": "does silsil"
  },
  "190": {
    "start": 565.63,
    "end": 570.429,
    "transcript": "oh yeah pharmacy yeah that's right uhm and the the pharmacy has a handle on the door"
  },
  "191": {
    "start": 571.81,
    "end": 573.419,
    "transcript": "and is it sort of pinky colour"
  },
  "192": {
    "start": 574.61,
    "end": 576.719,
    "transcript": "yeah and underneath the sort of"
  },
  "193": {
    "start": 577.27337,
    "end": 579.689,
    "transcript": "uh the blue vase thing is it sort of"
  },
  "194": {
    "start": 580.98,
    "end": 584.389,
    "transcript": "yeah but underneath that is there kind of a grill sort yeah"
  },
  "195": {
    "start": 584.61,
    "end": 585.13069,
    "transcript": "okay"
  },
  "196": {
    "start": 586.28129,
    "end": 591.809,
    "transcript": "uhm hmm how many splodges does the butcher have on the upper part of his apron"
  },
  "197": {
    "start": 592.65,
    "end": 593.34,
    "transcript": "and the bottom"
  },
  "198": {
    "start": 593.98,
    "end": 594.709,
    "transcript": "yeah and two"
  },
  "199": {
    "start": 595.11,
    "end": 595.399,
    "transcript": "yeah"
  },
  "200": {
    "start": 596.22,
    "end": 599.68,
    "transcript": "yeah same and he's holding a cleaver and that also has blood on it yeah"
  },
  "201": {
    "start": 601.18946,
    "end": 602.85,
    "transcript": "ooh"
  },
  "202": {
    "start": 605.82,
    "end": 606.149,
    "transcript": "yeah"
  },
  "203": {
    "start": 606.54,
    "end": 607.85735,
    "transcript": "all in green"
  },
  "204": {
    "start": 608.21,
    "end": 609.44683,
    "transcript": "yeah uhm"
  },
  "205": {
    "start": 610.89,
    "end": 611.279,
    "transcript": "yeah"
  },
  "206": {
    "start": 611.61,
    "end": 612.97,
    "transcript": "yeah uhm"
  },
  "207": {
    "start": 614.6995,
    "end": 616.55273,
    "transcript": "uh argh"
  }
}